antu/__init__.py
antu/io/__init__.py
antu/io/ext_embedding_readers.py
antu/io/instance.py
antu/io/instance_test.py
antu/io/vocabulary.py
antu/io/vocabulary_test.py
antu/io/configurators/__init__.py
antu/io/configurators/ini_configurator.py
antu/io/configurators/ini_configurator_test.py
antu/io/dataset_readers/__init__.py
antu/io/dataset_readers/dataset_reader.py
antu/io/datasets/__init__.py
antu/io/datasets/dataset.py
antu/io/datasets/single_task_dataset.py
antu/io/fields/__init__.py
antu/io/fields/field.py
antu/io/fields/index_field.py
antu/io/fields/sequence_label_field.py
antu/io/fields/text_field.py
antu/io/fields/text_field_test.py
antu/io/token_indexers/__init__.py
antu/io/token_indexers/char_token_indexer.py
antu/io/token_indexers/char_token_indexer_test.py
antu/io/token_indexers/single_id_token_indexer.py
antu/io/token_indexers/single_id_token_indexer_test.py
antu/io/token_indexers/token_indexer.py
antu/nn/__init__.py
antu/nn/dynet/BERT.py
antu/nn/dynet/__init__.py
antu/nn/dynet/attention_mechanism.py
antu/nn/dynet/char2word_embedder.py
antu/nn/dynet/feed_forward.py
antu/nn/dynet/gelu.py
antu/nn/dynet/initializer.py
antu/nn/dynet/layer_norm.py
antu/nn/dynet/linear.py
antu/nn/dynet/multi_layer_perception.py
antu/nn/dynet/nn_classifier.py
antu/nn/dynet/sublayer.py
antu/nn/dynet/transformer.py
antu/nn/dynet/attention/__init__.py
antu/nn/dynet/attention/biaffine.py
antu/nn/dynet/attention/multi_head.py
antu/nn/dynet/attention/single.py
antu/nn/dynet/embedding/__init__.py
antu/nn/dynet/embedding/bert.py
antu/nn/dynet/embedding/position.py
antu/nn/dynet/embedding/segment.py
antu/nn/dynet/embedding/token.py
antu/nn/dynet/seq2seq_encoders/__init__.py
antu/nn/dynet/seq2seq_encoders/rnn_builder.py
antu/nn/dynet/seq2seq_encoders/seq2seq_encoder.py
antu/utils/__init__.py
antu/utils/case_sensitive_configurator.py
antu/utils/dual_channel_logger.py
antu/utils/padding_function.py
antu-0.0.4.dist-info/LICENSE
antu-0.0.4.dist-info/METADATA
antu-0.0.4.dist-info/WHEEL
antu-0.0.4.dist-info/top_level.txt
antu-0.0.4.dist-info/zip-safe
antu-0.0.4.dist-info/RECORD
