Metadata-Version: 2.1
Name: antu
Version: 0.0.4
Summary: Universal data IO and neural network modules in NLP tasks
Home-page: https://github.com/AntNLP/antu
Author: AntNLP
Author-email: taoji.cs@gmail.com
License: Apache
Platform: any
Classifier: License :: OSI Approved :: Apache Software License
Classifier: Programming Language :: Python :: 3 :: Only
Classifier: Topic :: Documentation :: Sphinx
Classifier: Topic :: Scientific/Engineering :: Artificial Intelligence
